cpp_backend.cpython-39-darwin.so
sarina/__main__.py
sarina/parsers.py
sarina/py2cpp.py
sarina/assets/.DS_Store
sarina/assets/images/.DS_Store
sarina/assets/images/Sarina.png
sarina/assets/images/iran_map.png
sarina/assets/texts/heroes_of_iran.txt
sarina/lib/cpp_backend.cpp
sarina_cli-0.0.12.dist-info/LICENSE
sarina_cli-0.0.12.dist-info/METADATA
sarina_cli-0.0.12.dist-info/WHEEL
sarina_cli-0.0.12.dist-info/entry_points.txt
sarina_cli-0.0.12.dist-info/top_level.txt
sarina_cli-0.0.12.dist-info/RECORD
