Metadata-Version: 2.1
Name: sarina-cli
Version: 0.0.12
Summary: ASCII Art Generator
Home-page: https://github.com/AminAlam/Sarina
Author: Amin Alam
License: MIT
Keywords: ASCII-Art Word-Cloud-Generator
Requires-Python: >=3.5
License-File: LICENSE
Requires-Dist: tqdm (>=4.64.1)
Requires-Dist: click (>=8.1.3)
Requires-Dist: numpy (>=1.24.1)
Requires-Dist: opencv-python (>=4.7.0.68)
